runtime_yolk/__init__.py
runtime_yolk/config_loader.py
runtime_yolk/env_cli.py
runtime_yolk/env_loader.py
runtime_yolk/py.typed
runtime_yolk/yolk.py
runtime_yolk/util/__init__.py
runtime_yolk/util/file_rule.py
runtime_yolk-1.2.3.dist-info/LICENSE
runtime_yolk-1.2.3.dist-info/METADATA
runtime_yolk-1.2.3.dist-info/WHEEL
runtime_yolk-1.2.3.dist-info/entry_points.txt
runtime_yolk-1.2.3.dist-info/top_level.txt
runtime_yolk-1.2.3.dist-info/RECORD
