Metadata-Version: 2.1
Name: runtime-yolk
Version: 1.2.3
Summary: This project aims to create a single library for run-time initiation tasks that are often duplicated across many projects.
Author-email: Preocts <preocts@preocts.com>
License: MIT License
Project-URL: homepage, https://github.com/Preocts/runtime-yolk
Classifier: License :: OSI Approved :: MIT License
Classifier: Programming Language :: Python :: 3
Classifier: Programming Language :: Python :: 3 :: Only
Classifier: Programming Language :: Python :: Implementation :: CPython
Requires-Python: >=3.8
License-File: LICENSE
Provides-Extra: dev
Requires-Dist: pre-commit ; extra == 'dev'
Requires-Dist: black ; extra == 'dev'
Requires-Dist: mypy ; extra == 'dev'
Requires-Dist: flake8 ; extra == 'dev'
Requires-Dist: flake8-builtins ; extra == 'dev'
Provides-Extra: test
Requires-Dist: pytest ; extra == 'test'
Requires-Dist: pytest-randomly ; extra == 'test'
Requires-Dist: coverage ; extra == 'test'
Requires-Dist: tox ; extra == 'test'
